prowlarr/__init__.py
prowlarr/api_client.py
prowlarr/api_response.py
prowlarr/configuration.py
prowlarr/exceptions.py
prowlarr/py.typed
prowlarr/rest.py
prowlarr/api/__init__.py
prowlarr/api/api_info_api.py
prowlarr/api/app_profile_api.py
prowlarr/api/application_api.py
prowlarr/api/authentication_api.py
prowlarr/api/backup_api.py
prowlarr/api/command_api.py
prowlarr/api/custom_filter_api.py
prowlarr/api/development_config_api.py
prowlarr/api/download_client_api.py
prowlarr/api/download_client_config_api.py
prowlarr/api/file_system_api.py
prowlarr/api/health_api.py
prowlarr/api/history_api.py
prowlarr/api/host_config_api.py
prowlarr/api/indexer_api.py
prowlarr/api/indexer_default_categories_api.py
prowlarr/api/indexer_proxy_api.py
prowlarr/api/indexer_stats_api.py
prowlarr/api/indexer_status_api.py
prowlarr/api/localization_api.py
prowlarr/api/log_api.py
prowlarr/api/log_file_api.py
prowlarr/api/newznab_api.py
prowlarr/api/notification_api.py
prowlarr/api/ping_api.py
prowlarr/api/search_api.py
prowlarr/api/static_resource_api.py
prowlarr/api/system_api.py
prowlarr/api/tag_api.py
prowlarr/api/tag_details_api.py
prowlarr/api/task_api.py
prowlarr/api/ui_config_api.py
prowlarr/api/update_api.py
prowlarr/api/update_log_file_api.py
prowlarr/models/__init__.py
prowlarr/models/api_info_resource.py
prowlarr/models/app_profile_resource.py
prowlarr/models/application_bulk_resource.py
prowlarr/models/application_resource.py
prowlarr/models/application_sync_level.py
prowlarr/models/apply_tags.py
prowlarr/models/authentication_required_type.py
prowlarr/models/authentication_type.py
prowlarr/models/backup_resource.py
prowlarr/models/backup_type.py
prowlarr/models/book_search_param.py
prowlarr/models/certificate_validation_type.py
prowlarr/models/command.py
prowlarr/models/command_priority.py
prowlarr/models/command_resource.py
prowlarr/models/command_status.py
prowlarr/models/command_trigger.py
prowlarr/models/contract_field.py
prowlarr/models/custom_filter_resource.py
prowlarr_py-1.1.0.dist-info/LICENSE
prowlarr_py-1.1.0.dist-info/METADATA
prowlarr_py-1.1.0.dist-info/WHEEL
prowlarr_py-1.1.0.dist-info/top_level.txt
prowlarr_py-1.1.0.dist-info/RECORD
